README.md
setup.py
ortools_utils/__init__.py
ortools_utils/callbacks.py
ortools_utils/hinting.py
ortools_utils/model.py
ortools_utils.egg-info/PKG-INFO
ortools_utils.egg-info/SOURCES.txt
ortools_utils.egg-info/dependency_links.txt
ortools_utils.egg-info/requires.txt
ortools_utils.egg-info/top_level.txt