Metadata-Version: 2.1
Name: ortools-utils
Version: 0.0.6
Summary: Python utilities for ortools
Home-page: https://github.com/stradivari96/ortools-utils
Author: Xiang Chen
Author-email: xiangchenchen96@gmail.com
License: UNKNOWN
Platform: UNKNOWN
Classifier: Programming Language :: Python :: 3
Classifier: License :: OSI Approved :: MIT License
Classifier: Operating System :: OS Independent
Requires-Python: >=3.6
